{
  "tos": {
    "version": "1.2",
    "acceptedOn": "2026-02-15T04:10:09.636Z"
  },
  "billboardData": {
    "atlasUrl": "https://raw.githubusercontent.com/Mineblown/smashedgroups/main/28_billboard_atlas.png?v=1771128667538",
    "images": [
      {
        "name": "C1116467-811A-43A8-A8D9-EDB6A3F5C541.png",
        "uv": [
          0,
          0,
          0.5,
          0.3333333333333333
        ]
      },
      {
        "name": "NEW_BANNER_RATED_R_sticker.png",
        "uv": [
          0.5,
          0,
          0.5,
          0.3333333333333333
        ]
      },
      {
        "name": "Untitled_design_58.png",
        "uv": [
          0,
          0.3333333333333333,
          0.5,
          0.3333333333333333
        ]
      },
      {
        "name": "oeVt4Ub.png",
        "uv": [
          0.5,
          0.3333333333333333,
          0.5,
          0.3333333333333333
        ]
      },
      {
        "name": "waypoint.png",
        "uv": [
          0,
          0.6666666666666666,
          0.5,
          0.3333333333333333
        ]
      }
    ]
  },
  "groupName": "Taco's",
  "tagline": "Party like legends",
  "discord": "https://discord.gg/MyRFQjpRzc",
  "vrchat": "grp_3efba4a4-18d7-43ec-b8ef-1cafd9cec1c4/settings/logs",
  "youtube": "",
  "tiktok": "",
  "instagram": "",
  "x": "",
  "patreon": "",
  "rules": "📜 RULES TO KEEP THE VIBE STRONG: 🔞 18+ ONLY. <br>Security will be checking at the door. 💢 <br>Leave the drama at home — we’re all grown-ass adults. <br>🤝Respect everyone. No racism, no hate — we thrive on diversity. <br>🎧 If there’s a DJ playing, do NOT micspam your music. <br>🛡️ Show respect to our Mods and Staff — they’re here for your vibe & safety.Let the bass hit, not your attitude.<br><br>",
  "infoBoard": "<color=#FF0000>❤️‍🔥 Welcome to Taco's ❤️‍🔥</color>  <b>Hosted by TwerkTaco & The Hood — Party like legends.</b>  <br>Register on our website: https://tacosvr.chat<br><br><br>",
  "groupPhotosEnabled": true,
  "moderators": [
    "TwerkTaco",
    "zencat__",
    "NaughteeNoodle",
    "࿇R E S O L V E࿇",
    "TheIllusionJedi",
    "-_-Nëø-_-",
    "TheBlitz_",
    "gravygriller",
    "DecaySchulz",
    "AlexCorruptor",
    "༒Niki༒",
    "Rjdaonetobeat",
    "Ｇalaxy",
    "༺ღʟᴜᴄʏᴅʀᴇᴀᴍsღ༻",
    "Plutto2Times",
    "Domwan",
    "⭐ WesGG ⭐",
    "Blazinn420",
    "༺ღ༒Angel༒ღ༻"
  ],
  "owners": [
    "TwerkTaco"
  ],
  "coOwners": [],
  "landingPageUrl": "https://vrclink.com/p/tacos",
  "active": true,
  "posterEnabled": true
}