{
  "billboardData": {
    "atlasUrl": "https://raw.githubusercontent.com/Mineblown/smashedgroups/main/3333331_billboard_atlas.png",
    "images": [
      {
        "name": "chess text.png",
        "uv": [
          0,
          0,
          0.5,
          0.3333333333333333
        ]
      },
      {
        "name": "gunfirefalls.png",
        "uv": [
          0.5,
          0,
          0.5,
          0.3333333333333333
        ]
      },
      {
        "name": "IMG_5222.jpg",
        "uv": [
          0,
          0.3333333333333333,
          0.5,
          0.3333333333333333
        ]
      },
      {
        "name": "IMG_5222.png",
        "uv": [
          0.5,
          0.3333333333333333,
          0.5,
          0.3333333333333333
        ]
      },
      {
        "name": "rozAhai.png",
        "uv": [
          0,
          0.6666666666666666,
          0.5,
          0.3333333333333333
        ]
      }
    ]
  },
  "rules": "dasasdads<br>das<br>ads<br>asd",
  "posters": true,
  "moderators": [
    "dasdsadas"
  ],
  "discord": "http://asddasasd.com",
  "vrchat": "http://asddasasd.com",
  "groupName": "asdsadasddsa"
}